genki_signals/__init__.py
genki_signals/buffers.py
genki_signals/dead_reckoning.py
genki_signals/filters.py
genki_signals/fusion.py
genki_signals/recorders.py
genki_signals/session.py
genki_signals/system.py
genki_signals/frontends/__init__.py
genki_signals/frontends/base.py
genki_signals/frontends/visualization.py
genki_signals/functions/__init__.py
genki_signals/functions/arithmetic.py
genki_signals/functions/base.py
genki_signals/functions/filters.py
genki_signals/functions/geometry.py
genki_signals/functions/inference.py
genki_signals/functions/serialization.py
genki_signals/functions/shape.py
genki_signals/functions/waveforms.py
genki_signals/functions/windowed.py
genki_signals/models/letter_detection_model.py
genki_signals/sources/__init__.py
genki_signals/sources/base.py
genki_signals/sources/ble.py
genki_signals/sources/dataframe.py
genki_signals/sources/generators.py
genki_signals/sources/local.py
genki_signals/sources/sampler.py
genki_signals/sources/wave.py
genki_signals-0.1.1.dist-info/METADATA
genki_signals-0.1.1.dist-info/WHEEL
genki_signals-0.1.1.dist-info/top_level.txt
genki_signals-0.1.1.dist-info/RECORD
