Metadata-Version: 2.1
Name: genki-signals
Version: 0.1.1
Summary: A library for realtime signal processing and machine learning
Home-page: https://github.com/genkiinstruments/genki-signals
Author: Genki Instruments
Author-email: genki@genkiinstruments.com
Keywords: Signal Processing,Machine Learning,Realtime
Classifier: License :: OSI Approved :: MIT License
Classifier: Programming Language :: Python
Classifier: Programming Language :: Python :: 3
Requires-Python: >=3.9
Requires-Dist: numpy
Requires-Dist: pandas
Requires-Dist: scipy
Requires-Dist: onnx
Requires-Dist: onnxruntime
Requires-Dist: opencv-python
Requires-Dist: pynput
Requires-Dist: bqplot
Requires-Dist: ipywidgets
Requires-Dist: IPython
Requires-Dist: ahrs
Requires-Dist: imufusion
Requires-Dist: bleak
Requires-Dist: genki-wave
